MANIFEST.in
setup.cfg
setup.py
tests/test_cli.py
tests/__pycache__/test_cli.cpython-36-PYTEST.pyc
tests/commands/test_hello.py
tests/commands/__pycache__/test_hello.cpython-36-PYTEST.pyc
toolk/__init__.py
toolk/cli.py
toolk/commands/__init__.py
toolk/commands/base.py
toolk/commands/generate.py
toolk/commands/messages.py
toolk/templates/__init__.py
toolk/templates/viewControllerTemplate.py