Metadata-Version: 1.1
Name: toolk
Version: 0.0.8
Summary: CLI toolkit for managing Swift projects in Xcode
Home-page: https://github.com/Alphazella/toolk
Author: Heinrich Tremblay
Author-email: heinrich.tremblay@hec.ca
License: MIT License
Keywords: cli
Platform: UNKNOWN
Classifier: Intended Audience :: Developers
Classifier: Topic :: Utilities
Classifier: License :: OSI Approved :: MIT License
Classifier: Natural Language :: English
Classifier: Operating System :: OS Independent
Classifier: Programming Language :: Python :: 2
Classifier: Programming Language :: Python :: 2.6
Classifier: Programming Language :: Python :: 2.7
Classifier: Programming Language :: Python :: 3
Classifier: Programming Language :: Python :: 3.2
Classifier: Programming Language :: Python :: 3.3
Classifier: Programming Language :: Python :: 3.4
